salve/__init__.py
salve/ipc.py
salve/misc.py
salve/wrappers.py
salve/server_functions/__init__.py
salve/server_functions/autocompletions.py
salve/server_functions/definitions.py
salve/server_functions/links_and_hidden_chars.py
salve/server_functions/misc.py
salve/server_functions/replacements.py
salve/server_functions/highlight/__init__.py
salve/server_functions/highlight/docstring_highlight.py
salve/server_functions/highlight/highlight.py
salve/server_functions/highlight/misc.py
salve-1.2.0.dist-info/LICENSE
salve-1.2.0.dist-info/METADATA
salve-1.2.0.dist-info/WHEEL
salve-1.2.0.dist-info/top_level.txt
salve-1.2.0.dist-info/RECORD
