Metadata-Version: 2.1
Name: salve
Version: 1.2.0
Summary: Salve is an IPC library that can be used by code editors to easily get autocompletions, replacements, editorconfig suggestions, definitions, and syntax highlighting.
Home-page: https://github.com/salve-org/salve
Author: Moosems
Author-email: moosems.j@gmail.com
License: MIT license
Classifier: Development Status :: 3 - Alpha
Classifier: Operating System :: OS Independent
Classifier: Programming Language :: Python :: Implementation
Classifier: Intended Audience :: Developers
Classifier: License :: OSI Approved :: MIT License
Classifier: Typing :: Typed
Requires-Python: >=3.11
License-File: LICENSE
Requires-Dist: pygments
Requires-Dist: pyeditorconfig
Requires-Dist: beartype
Requires-Dist: token-tools
Requires-Dist: collegamento
